d_flip_flop/design.sv
// Design
// D flip-flop
module dff (clk, reset,
  d, q, qb);
  input      clk;
  input      reset;
  input      d;
  output     q;
  output     qb;

  reg        q;

  assign qb = ~q;

  initial $display("Hello");
  
  always @(posedge clk or posedge reset)
  begin
    if (reset) begin
      // Asynchronous reset when reset goes high
      q <= 1'b0;
    end else begin
      // Assign D to Q on positive clock edge
      q <= d;
    end
  end
endmodule

d_flip_flop/testbench.sv
// Testbench
module test;

  reg clk;
  reg reset;
  reg d;
  wire q;
  wire qb;
  
  // Instantiate design under test
  dff DFF(.clk(clk), .reset(reset), .d(d), .q(q), .qb(qb));

  initial begin
    // Dump waves
    $dumpfile("test.vcd");
    $dumpvars(0, test);
    
    $display("Reset flop.");
    clk = 0;
    reset = 1;
    d = 1'bx;
    display;
    
    $display("Release reset.");
    d = 1;
    reset = 0;
    display;

    $display("Toggle clk.");
    clk = 1;
    display;

    for (int i = 0; i < 10; i++) begin
      clk = ~clk; // Toggle clock
      display; // Display current state
      end

  end
  
  task display;
    #1 $display("d:%0h, q:%0h, qb:%0h",
      d, q, qb);
  endtask

endmodule

d_flip_flop/test.vcd
$version Generated by VerilatedVcd $end
$timescale 1ps $end
 $scope module $rootio $end
 $upscope $end
 $scope module test $end
  $var wire 1 # clk $end
  $var wire 1 $ reset $end
  $var wire 1 % d $end
  $var wire 1 & q $end
  $var wire 1 ' qb $end
  $scope module DFF $end
   $var wire 1 # clk $end
   $var wire 1 $ reset $end
   $var wire 1 % d $end
   $var wire 1 & q $end
   $var wire 1 ' qb $end
  $upscope $end
  $scope module unnamedblk1 $end
   $var wire 32 ( i [31:0] $end
  $upscope $end
 $upscope $end
$enddefinitions $end


#0
0#
1$
0%
0&
1'
b00000000000000000000000000000000 (
#1
0$
1%
#2
1#
1&
0'
#3
0#
#4
1#
b00000000000000000000000000000001 (
#5
0#
b00000000000000000000000000000010 (
#6
1#
b00000000000000000000000000000011 (
#7
0#
b00000000000000000000000000000100 (
#8
1#
b00000000000000000000000000000101 (
#9
0#
b00000000000000000000000000000110 (
#10
1#
b00000000000000000000000000000111 (
#11
0#
b00000000000000000000000000001000 (
#12
1#
b00000000000000000000000000001001 (
#13
b00000000000000000000000000001010 (
